[{
  "id": 1,
  "title": "Уровень карналита в силостной башне",
  "value": 1065,
  "minValue": 450,
  "maxValue": 1100
}, {
  "id": 2,
  "title": "Уровень карналита в силостной башне",
  "value": 1200,
  "minValue": 500,
  "maxValue": 1500
}, {
  "id": 3,
  "title": "Уровень карналита в силостной башне",
  "value": 700,
  "minValue": 300,
  "maxValue": 2600
}, {
  "id": 4,
  "title": "Уровень карналита в силостной башне",
  "value": 1540,
  "minValue": 150,
  "maxValue": 2750
}, {
  "id": 5,
  "title": "Уровень карналита в силостной башне",
  "value": 1505,
  "minValue": 500,
  "maxValue": 1300
}]
